cava_parser/__init__.py
cava_parser/cava_parser.py
cava_parser-0.1.0.dist-info/METADATA
cava_parser-0.1.0.dist-info/WHEEL
cava_parser-0.1.0.dist-info/RECORD
